<?xml version="1.0" encoding="utf-8" ?>
<dwsync>
<file name="banner1.swf" server="ftp.wesley.com.hk" local="129992731389875284" remote="130008984600000000" Dst="0" />
<file name="banner2.swf" server="ftp.wesley.com.hk" local="129992731390100395" remote="130008984600000000" Dst="0" />
<file name="banner3a.swf" server="ftp.wesley.com.hk" local="129992731390100395" remote="130008984600000000" Dst="0" />
<file name="banner3b.swf" server="ftp.wesley.com.hk" local="129992731390775297" remote="130008984600000000" Dst="0" />
<file name="banner3c.swf" server="ftp.wesley.com.hk" local="129992731391075402" remote="130008984600000000" Dst="0" />
<file name="bbk_FM.swf" server="ftp.wesley.com.hk" local="129992731392725491" remote="130008984600000000" Dst="0" />
<file name="index.html" server="ftp.wesley.com.hk" local="129992731394550512" remote="130008984600000000" Dst="0" />
<file name="index.php" server="ftp.wesley.com.hk" local="129992731395350563" remote="130008984600000000" Dst="0" />
<file name="mamaSite.swf" server="ftp.wesley.com.hk" local="129992731396025597" remote="130008984600000000" Dst="0" />
</dwsync>